{"id": "toasted-houston", "rating": 3.5, "coordinates": {"longitude": -95.4293202, "latitude": 29.8178465}, "is_claimed": true, "hours": [{"is_open_now": false, "open": [{"is_overnight": false, "day": 0, "start": "0630", "end": "1500"}, {"is_overnight": false, "day": 1, "start": "0630", "end": "1500"}, {"is_overnight": false, "day": 2, "start": "0630", "end": "1500"}, {"is_overnight": false, "day": 3, "start": "0630", "end": "1500"}, {"is_overnight": false, "day": 4, "start": "0630", "end": "1500"}, {"is_overnight": false, "day": 5, "start": "0700", "end": "1500"}, {"is_overnight": false, "day": 6, "start": "0700", "end": "1500"}], "hours_type": "REGULAR"}], "photos": ["https://s3-media1.fl.yelpcdn.com/bphoto/pn61Ch13Zrzls8PzFCY3Cw/o.jpg", "https://s3-media1.fl.yelpcdn.com/bphoto/LXCSxRAXzMGEj0y-sW960g/o.jpg", "https://s3-media3.fl.yelpcdn.com/bphoto/5LVPalNuJ84uFbMx_aajxw/o.jpg"], "review_count": 71, "price": "$", "term": "restaurants", "url": "https://www.yelp.com/biz/toasted-houston?adjust_creative=92p07_JjKyriZTQxAXRiKQ&utm_campaign=yelp_api_v3&utm_medium=api_v3_business_lookup&utm_source=92p07_JjKyriZTQxAXRiKQ", "categories": [{"alias": "sandwiches", "title": "Sandwiches"}, {"alias": "coffee", "title": "Coffee & Tea"}, {"alias": "bagels", "title": "Bagels"}], "location": {"address3": "", "zip_code": "77018", "address1": "3434 Ella Blvd", "address2": null, "city": "Houston", "state": "TX", "country": "US"}, "is_closed": false, "phone": "+12819743291", "image_url": "https://s3-media3.fl.yelpcdn.com/bphoto/pn61Ch13Zrzls8PzFCY3Cw/o.jpg", "name": "Toasted"}