{"id": "the-brentwood-inn-los-angeles", "rating": 4.5, "coordinates": {"longitude": -118.47829, "latitude": 34.05815}, "is_claimed": true, "photos": ["https://s3-media4.fl.yelpcdn.com/bphoto/ehQu-C59IVLrnhMm0_yL0Q/o.jpg", "https://s3-media1.fl.yelpcdn.com/bphoto/2HsgdxZ5mQmlig1kPt_NOg/o.jpg", "https://s3-media2.fl.yelpcdn.com/bphoto/fsyw43yEYRu3x6xGB94QuQ/o.jpg"], "review_count": 44, "price": "$$", "term": "hotels", "url": "https://www.yelp.com/biz/the-brentwood-inn-los-angeles?adjust_creative=92p07_JjKyriZTQxAXRiKQ&utm_campaign=yelp_api_v3&utm_medium=api_v3_business_lookup&utm_source=92p07_JjKyriZTQxAXRiKQ", "categories": [{"alias": "hotels", "title": "Hotels"}], "location": {"address3": "", "zip_code": "90049", "address1": "12200 W Sunset Blvd", "address2": "", "city": "Los Angeles", "state": "CA", "country": "US"}, "is_closed": false, "phone": "+13104769981", "image_url": "https://s3-media4.fl.yelpcdn.com/bphoto/ehQu-C59IVLrnhMm0_yL0Q/o.jpg", "name": "The Brentwood Inn"}