{"price": "$$", "rating": 4.0, "coordinates": {"longitude": -122.3020362854, "latitude": 47.613193657257}, "is_claimed": true, "hours": [{"is_open_now": false, "open": [{"is_overnight": true, "day": 0, "end": "0130", "start": "1200"}, {"is_overnight": true, "day": 1, "end": "0130", "start": "1200"}, {"is_overnight": true, "day": 2, "end": "0130", "start": "1200"}, {"is_overnight": true, "day": 3, "end": "0130", "start": "1200"}, {"is_overnight": true, "day": 4, "end": "0130", "start": "1200"}, {"is_overnight": true, "day": 5, "end": "0130", "start": "1200"}, {"is_overnight": true, "day": 6, "end": "0130", "start": "1200"}], "hours_type": "REGULAR"}], "photos": ["https://s3-media1.fl.yelpcdn.com/bphoto/Fny3Tzg6myhqtRO4BiebAA/o.jpg", "https://s3-media3.fl.yelpcdn.com/bphoto/HQBoxpGqNzXT7OLMHjyN7A/o.jpg", "https://s3-media2.fl.yelpcdn.com/bphoto/igA2awDusgXE5es9S4z93w/o.jpg"], "review_count": 119, "id": "the-neighbor-lady-seattle", "term": "restaurants", "url": "https://www.yelp.com/biz/the-neighbor-lady-seattle?adjust_creative=92p07_JjKyriZTQxAXRiKQ&utm_campaign=yelp_api_v3&utm_medium=api_v3_business_lookup&utm_source=92p07_JjKyriZTQxAXRiKQ", "categories": [{"alias": "bars", "title": "Bars"}, {"alias": "newamerican", "title": "American (New)"}], "location": {"address3": "", "zip_code": "98122", "address1": "2308 E Union St", "state": "WA", "city": "Seattle", "address2": "", "country": "US"}, "is_closed": false, "phone": "+12066952072", "image_url": "https://s3-media4.fl.yelpcdn.com/bphoto/Fny3Tzg6myhqtRO4BiebAA/o.jpg", "name": "The Neighbor Lady"}