{"id": "the-principal-brewing-company-midland", "rating": 4.0, "coordinates": {"longitude": 116.007103, "latitude": -31.8895798}, "is_claimed": false, "hours": [{"is_open_now": true, "open": [{"is_overnight": false, "day": 0, "start": "1000", "end": "2200"}, {"is_overnight": false, "day": 1, "start": "1000", "end": "2200"}, {"is_overnight": false, "day": 2, "start": "1000", "end": "2200"}, {"is_overnight": false, "day": 3, "start": "1000", "end": "2200"}, {"is_overnight": false, "day": 4, "start": "1000", "end": "2200"}, {"is_overnight": false, "day": 5, "start": "1000", "end": "2200"}, {"is_overnight": false, "day": 6, "start": "1000", "end": "2200"}], "hours_type": "REGULAR"}], "photos": ["https://s3-media4.fl.yelpcdn.com/bphoto/wEkpxPA2aQNxWWDQHHG3Ew/o.jpg", "https://s3-media1.fl.yelpcdn.com/bphoto/lg149Gmuv5hi6PNmlMa7UA/o.jpg", "https://s3-media4.fl.yelpcdn.com/bphoto/cIP_oRNQX7RifTO5BtT3Xg/o.jpg"], "review_count": 8, "price": "$$", "term": "attractions", "url": "https://www.yelp.com/biz/the-principal-brewing-company-midland?adjust_creative=92p07_JjKyriZTQxAXRiKQ&utm_campaign=yelp_api_v3&utm_medium=api_v3_business_lookup&utm_source=92p07_JjKyriZTQxAXRiKQ", "categories": [{"title": "Hotels", "alias": "hotels"}, {"title": "Bars", "alias": "bars"}, {"title": "Breweries", "alias": "breweries"}], "image_url": "https://s3-media4.fl.yelpcdn.com/bphoto/wEkpxPA2aQNxWWDQHHG3Ew/o.jpg", "is_closed": false, "phone": "+61892502995", "location": {"address3": null, "zip_code": "6056", "address1": "23 Cale St", "state": "WA", "city": "Midland", "address2": null, "country": "AU"}, "name": "The Principal Brewing Company"}