{"price": "$$$$", "rating": 4.0, "coordinates": {"longitude": -118.266978538154, "latitude": 34.0452601919365}, "is_claimed": true, "hours": [{"is_open_now": true, "open": [{"is_overnight": false, "end": "0000", "start": "0000", "day": 0}, {"is_overnight": false, "end": "0000", "start": "0000", "day": 1}, {"is_overnight": false, "end": "0000", "start": "0000", "day": 2}, {"is_overnight": false, "end": "0000", "start": "0000", "day": 3}, {"is_overnight": false, "end": "0000", "start": "0000", "day": 4}, {"is_overnight": false, "end": "0000", "start": "0000", "day": 5}, {"is_overnight": false, "end": "0000", "start": "0000", "day": 6}], "hours_type": "REGULAR"}], "photos": ["https://s3-media2.fl.yelpcdn.com/bphoto/rI10UmI_5S4bJKEnhrjyDw/o.jpg", "https://s3-media2.fl.yelpcdn.com/bphoto/-Zi2NXK5vLpfdjqYzwp6PA/o.jpg", "https://s3-media4.fl.yelpcdn.com/bphoto/XS_cZYlQ5Uqfdy2HvhqS4A/o.jpg"], "review_count": 163, "id": "the-ritz-carlton-los-angeles-los-angeles-4", "term": "attractions", "url": "https://www.yelp.com/biz/the-ritz-carlton-los-angeles-los-angeles-4?adjust_creative=92p07_JjKyriZTQxAXRiKQ&utm_campaign=yelp_api_v3&utm_medium=api_v3_business_lookup&utm_source=92p07_JjKyriZTQxAXRiKQ", "categories": [{"alias": "hotels", "title": "Hotels"}, {"alias": "venues", "title": "Venues & Event Spaces"}], "location": {"address3": "", "zip_code": "90015", "address1": "900 W Olympic Blvd", "state": "CA", "city": "Los Angeles", "address2": "", "country": "US"}, "is_closed": false, "phone": "+12137438800", "image_url": "https://s3-media1.fl.yelpcdn.com/bphoto/rI10UmI_5S4bJKEnhrjyDw/o.jpg", "name": "The Ritz-Carlton, Los Angeles"}