{"id": "the-marble-bar-adelaide", "rating": 3.0, "coordinates": {"longitude": 138.5956268, "latitude": -34.9262009}, "is_claimed": false, "hours": [{"is_open_now": true, "open": [{"is_overnight": true, "day": 0, "start": "0700", "end": "0200"}, {"is_overnight": true, "day": 1, "start": "0700", "end": "0200"}, {"is_overnight": true, "day": 2, "start": "0700", "end": "0200"}, {"is_overnight": true, "day": 3, "start": "0700", "end": "0500"}, {"is_overnight": true, "day": 4, "start": "0700", "end": "0500"}, {"is_overnight": true, "day": 5, "start": "0700", "end": "0500"}, {"is_overnight": true, "day": 6, "start": "1100", "end": "0500"}], "hours_type": "REGULAR"}], "photos": ["https://s3-media3.fl.yelpcdn.com/bphoto/JSRAi6sqti15BLe9xZHCAw/o.jpg", "https://s3-media3.fl.yelpcdn.com/bphoto/C8VrHG_hWfvsrPlOx4qyKw/o.jpg"], "review_count": 6, "price": "$$", "term": "hotels", "url": "https://www.yelp.com/biz/the-marble-bar-adelaide?adjust_creative=92p07_JjKyriZTQxAXRiKQ&utm_campaign=yelp_api_v3&utm_medium=api_v3_business_lookup&utm_source=92p07_JjKyriZTQxAXRiKQ", "categories": [{"alias": "hotels", "title": "Hotels"}], "location": {"address3": null, "zip_code": "5000", "address1": "109 Waymouth St", "address2": null, "city": "Adelaide", "state": "SA", "country": "AU"}, "is_closed": false, "phone": "+61882314602", "image_url": "https://s3-media4.fl.yelpcdn.com/bphoto/JSRAi6sqti15BLe9xZHCAw/o.jpg", "name": "The Marble Bar"}