{"price": "$$", "rating": 4.5, "coordinates": {"longitude": -121.96473, "latitude": 37.23404}, "is_claimed": true, "hours": [{"is_open_now": false, "open": [{"is_overnight": false, "end": "2130", "start": "0530", "day": 0}, {"is_overnight": false, "end": "2130", "start": "0530", "day": 1}, {"is_overnight": false, "end": "2130", "start": "0530", "day": 2}, {"is_overnight": false, "end": "2130", "start": "0530", "day": 3}, {"is_overnight": false, "end": "1800", "start": "0530", "day": 4}, {"is_overnight": false, "end": "1800", "start": "0730", "day": 5}, {"is_overnight": false, "end": "1930", "start": "0730", "day": 6}], "hours_type": "REGULAR"}], "photos": ["https://s3-media3.fl.yelpcdn.com/bphoto/wyrTTML7cAaHma8OFTIjtw/o.jpg", "https://s3-media3.fl.yelpcdn.com/bphoto/D4GSFPzkWnuGN6ejwaqN1g/o.jpg", "https://s3-media2.fl.yelpcdn.com/bphoto/PmGXjBYASMhyXPx5NsrWsg/o.jpg"], "review_count": 293, "id": "yogasource-los-gatos-los-gatos", "term": "attractions", "url": "https://www.yelp.com/biz/yogasource-los-gatos-los-gatos?adjust_creative=92p07_JjKyriZTQxAXRiKQ&utm_campaign=yelp_api_v3&utm_medium=api_v3_business_lookup&utm_source=92p07_JjKyriZTQxAXRiKQ", "categories": [{"title": "Yoga", "alias": "yoga"}, {"title": "Cycling Classes", "alias": "cyclingclasses"}], "image_url": "https://s3-media1.fl.yelpcdn.com/bphoto/wyrTTML7cAaHma8OFTIjtw/o.jpg", "is_closed": false, "phone": "+14084029642", "location": {"address3": "", "zip_code": "95032", "address1": "16185 Los Gatos Blvd", "address2": "", "city": "Los Gatos", "state": "CA", "country": "US"}, "name": "YogaSource Los Gatos"}