{"id": "vale-park-wallasey", "rating": 3.0, "coordinates": {"longitude": -3.0362, "latitude": 53.4329681}, "is_claimed": false, "photos": [], "review_count": 1, "term": "attractions", "url": "https://www.yelp.com/biz/vale-park-wallasey?adjust_creative=92p07_JjKyriZTQxAXRiKQ&utm_campaign=yelp_api_v3&utm_medium=api_v3_business_lookup&utm_source=92p07_JjKyriZTQxAXRiKQ", "categories": [{"alias": "localflavor", "title": "Local Flavor"}], "location": {"address3": "", "zip_code": "CH45 1LZ", "address1": "Vale Park Lodge", "address2": "Vale Park", "city": "Wallasey", "state": "XMS", "country": "GB"}, "is_closed": false, "phone": "+441516306044", "image_url": "", "name": "Vale Park"}