{"price": "$", "rating": 4.0, "coordinates": {"longitude": -95.3618420932421, "latitude": 29.7621854179471}, "is_claimed": true, "hours": [{"is_open_now": false, "open": [{"is_overnight": false, "day": 0, "start": "1100", "end": "1430"}, {"is_overnight": false, "day": 1, "start": "1100", "end": "1430"}, {"is_overnight": false, "day": 2, "start": "1100", "end": "1430"}, {"is_overnight": false, "day": 3, "start": "1100", "end": "1430"}, {"is_overnight": false, "day": 4, "start": "1100", "end": "1430"}], "hours_type": "REGULAR"}], "photos": ["https://s3-media4.fl.yelpcdn.com/bphoto/rGMHxMjR6YoBnqxp6Mjs1A/o.jpg", "https://s3-media1.fl.yelpcdn.com/bphoto/8mhkD5Oq0INmk40yt-Oh-Q/o.jpg", "https://s3-media4.fl.yelpcdn.com/bphoto/fvQLoecf5c8jhr6R8_Tx_g/o.jpg"], "review_count": 155, "id": "treebeards-houston", "term": "restaurants", "url": "https://www.yelp.com/biz/treebeards-houston?adjust_creative=92p07_JjKyriZTQxAXRiKQ&utm_campaign=yelp_api_v3&utm_medium=api_v3_business_lookup&utm_source=92p07_JjKyriZTQxAXRiKQ", "categories": [{"alias": "cajun", "title": "Cajun/Creole"}, {"alias": "southern", "title": "Southern"}], "location": {"address3": "", "zip_code": "77002", "address1": "315 Travis St", "address2": "", "city": "Houston", "state": "TX", "country": "US"}, "is_closed": false, "phone": "+17132282622", "image_url": "https://s3-media1.fl.yelpcdn.com/bphoto/rGMHxMjR6YoBnqxp6Mjs1A/o.jpg", "name": "Treebeards"}