{"price": "\u00a3\u00a3", "rating": 4.5, "coordinates": {"longitude": -0.189546, "latitude": 51.5155202}, "is_claimed": true, "hours": [{"is_open_now": false, "open": [{"is_overnight": true, "end": "0100", "start": "1830", "day": 1}, {"is_overnight": true, "end": "0100", "start": "1830", "day": 2}, {"is_overnight": true, "end": "0100", "start": "1830", "day": 3}, {"is_overnight": true, "end": "0100", "start": "1830", "day": 4}, {"is_overnight": true, "end": "0100", "start": "1830", "day": 5}, {"is_overnight": false, "end": "2300", "start": "1830", "day": 6}], "hours_type": "REGULAR"}], "photos": ["https://s3-media1.fl.yelpcdn.com/bphoto/rpk_40vKhiOWm28ynWXgKQ/o.jpg", "https://s3-media2.fl.yelpcdn.com/bphoto/tDGelxXEqpiSBl9t8kGWfQ/o.jpg", "https://s3-media2.fl.yelpcdn.com/bphoto/VZ5uXOIIf_rqj2dd-iwyQw/o.jpg"], "review_count": 62, "id": "the-tiroler-hut-restaurant-london", "term": "restaurants", "url": "https://www.yelp.com/biz/the-tiroler-hut-restaurant-london?adjust_creative=92p07_JjKyriZTQxAXRiKQ&utm_campaign=yelp_api_v3&utm_medium=api_v3_business_lookup&utm_source=92p07_JjKyriZTQxAXRiKQ", "categories": [{"title": "German", "alias": "german"}, {"title": "Austrian", "alias": "austrian"}, {"title": "Fondue", "alias": "fondue"}], "image_url": "https://s3-media1.fl.yelpcdn.com/bphoto/rpk_40vKhiOWm28ynWXgKQ/o.jpg", "is_closed": false, "phone": "+442077273981", "location": {"address3": "", "zip_code": "W2 4UA", "address1": "27 Westbourne Grove", "address2": "", "city": "London", "state": "XGL", "country": "GB"}, "name": "The Tiroler Hut Restaurant"}