{"url": "https://www.yelp.com/biz/tiritiri-matangi-island-bunkhouse-auckland?adjust_creative=92p07_JjKyriZTQxAXRiKQ&utm_campaign=yelp_api_v3&utm_medium=api_v3_business_lookup&utm_source=92p07_JjKyriZTQxAXRiKQ", "rating": 5.0, "image_url": "https://s3-media2.fl.yelpcdn.com/bphoto/oO_Nhdqi9hiL2jb89flICQ/o.jpg", "is_closed": false, "review_count": 1, "phone": "+6494257812", "is_claimed": false, "term": "hotels", "location": {"zip_code": "", "city": "Auckland", "address3": "", "address1": "Tiritiri Matangi Island", "address2": "Hauraki Gulf", "country": "NZ", "state": "AUK"}, "categories": [{"title": "Local Flavor", "alias": "localflavor"}, {"title": "Hostels", "alias": "hostels"}], "photos": ["https://s3-media1.fl.yelpcdn.com/bphoto/oO_Nhdqi9hiL2jb89flICQ/o.jpg"], "name": "Tiritiri Matangi Island Bunkhouse", "coordinates": {"latitude": -36.8484597, "longitude": 174.7633315}, "id": "tiritiri-matangi-island-bunkhouse-auckland"}