{"id": "wunderlich-park-woodside", "rating": 4.5, "coordinates": {"longitude": -122.2605, "latitude": 37.40848}, "is_claimed": false, "hours": [{"is_open_now": false, "open": [{"is_overnight": false, "day": 0, "start": "0800", "end": "1800"}, {"is_overnight": false, "day": 1, "start": "0800", "end": "1800"}, {"is_overnight": false, "day": 2, "start": "0800", "end": "1800"}, {"is_overnight": false, "day": 3, "start": "0800", "end": "1800"}, {"is_overnight": false, "day": 4, "start": "0800", "end": "1800"}, {"is_overnight": false, "day": 5, "start": "0800", "end": "1800"}, {"is_overnight": false, "day": 6, "start": "0800", "end": "1800"}], "hours_type": "REGULAR"}], "photos": ["https://s3-media3.fl.yelpcdn.com/bphoto/QowD0HUajtaiLlhi3JMT7Q/o.jpg", "https://s3-media3.fl.yelpcdn.com/bphoto/djRQHgSgY5FH9LC8vpRohg/o.jpg", "https://s3-media2.fl.yelpcdn.com/bphoto/6k2C5VknVjr33uxOoMGl1w/o.jpg"], "review_count": 83, "term": "attractions", "url": "https://www.yelp.com/biz/wunderlich-park-woodside?adjust_creative=92p07_JjKyriZTQxAXRiKQ&utm_campaign=yelp_api_v3&utm_medium=api_v3_business_lookup&utm_source=92p07_JjKyriZTQxAXRiKQ", "categories": [{"alias": "parks", "title": "Parks"}, {"alias": "hiking", "title": "Hiking"}], "location": {"address3": "", "zip_code": "94062", "address1": "4040 Woodside Rd", "address2": "", "city": "Woodside", "state": "CA", "country": "US"}, "is_closed": false, "phone": "+16508511210", "image_url": "https://s3-media1.fl.yelpcdn.com/bphoto/QowD0HUajtaiLlhi3JMT7Q/o.jpg", "name": "Wunderlich Park"}